FieldEmission/__init__.py
FieldEmission/dataProvider.py
FieldEmission/feFormulas.py
FieldEmission/fileReader.py
FieldEmission-0.1.5.dist-info/METADATA
FieldEmission-0.1.5.dist-info/WHEEL
FieldEmission-0.1.5.dist-info/top_level.txt
FieldEmission-0.1.5.dist-info/RECORD
