Metadata-Version: 2.1
Name: FieldEmission
Version: 0.1.5
Summary: Field Emission Data Postprocessing and Data Provider
Home-page: https://github.com/Dephrilibrium/PythonFieldEmission
Author: haum@oth
Author-email: <matthias.hausladen@oth-regensburg.de>
Keywords: python,Cold Field Emission,Fowler Nordheim
Classifier: Development Status :: 1 - Planning
Classifier: Intended Audience :: End Users/Desktop
Classifier: Programming Language :: Python :: 3
Classifier: Operating System :: Microsoft :: Windows
Requires-Dist: numpy
Requires-Dist: scipy
